planship/__init__.py
planship/auto_refresh_token_api_client.py
planship/base.py
planship/http_basic_auth_configuration.py
planship/models.py
planship/planship.py
planship-0.2.0.dist-info/METADATA
planship-0.2.0.dist-info/WHEEL
planship-0.2.0.dist-info/top_level.txt
planship-0.2.0.dist-info/RECORD
