Metadata-Version: 2.1
Name: planship
Version: 0.2.0
Summary: Planship API client
Home-page: https://planship.io
Author: Pawel Wojnarowicz
Author-email: pawel@planship.io
Project-URL: Repository, https://github.com/planship/planship-python
Project-URL: Documentation, https://docs.planship.io
Keywords: Planship
Requires-Python: >=3.7
Requires-Dist: planship-openapi-gen >=1
